dltnchecker/__init__.py
dltnchecker/harvest.py
harvest/__init__.py
harvest/harvest.py
tests/__init__.py
tests/tests.py
dltn_checker-0.0.2.dist-info/METADATA
dltn_checker-0.0.2.dist-info/WHEEL
dltn_checker-0.0.2.dist-info/top_level.txt
dltn_checker-0.0.2.dist-info/RECORD
