Metadata-Version: 2.1
Name: dltn-checker
Version: 0.0.2
Summary: a simple utility to check and harvest metadata records from an OAI request when they meet theDLTN requirements
Home-page: https://github.com/DigitalLibraryofTennessee/check_and_harvest
Author: Mark Baggett
Author-email: mbagget1@utk.edu
Maintainer-email: mbagget1@utk.edu
License: UNKNOWN
Keywords: libraries,dpla,dltn,oaipmh,aggregators
Platform: UNKNOWN
Classifier: License :: OSI Approved :: GNU General Public License v3 (GPLv3)
Classifier: Programming Language :: Python :: 3.7
Classifier: Operating System :: OS Independent
Requires-Dist: requests (>=2.21.0)
Requires-Dist: xmltodict (>=0.12.0)
Requires-Dist: lxml (>=4.3.1)
Requires-Dist: repox (>=0.0.2)
Requires-Dist: pyyaml (>=4.2b1)
